<annotation>
	<folder></folder>
	<filename>brown_blight_in_tea40_jpg.rf.3ebbd17910a059c9dce4b35e2f764682.jpg</filename>
	<path>brown_blight_in_tea40_jpg.rf.3ebbd17910a059c9dce4b35e2f764682.jpg</path>
	<source>
		<database>roboflow.ai</database>
	</source>
	<size>
		<width>320</width>
		<height>320</height>
		<depth>3</depth>
	</size>
	<segmented>0</segmented>
	<object>
		<name>Brown Blight</name>
		<pose>Unspecified</pose>
		<truncated>0</truncated>
		<difficult>0</difficult>
		<occluded>0</occluded>
		<bndbox>
			<xmin>16</xmin>
			<xmax>216</xmax>
			<ymin>39</ymin>
			<ymax>273</ymax>
		</bndbox>
	</object>
</annotation>
