<annotation>
	<folder></folder>
	<filename>brown_blight_in_tea11_jpg.rf.849483c9693f6d1e2a253d666d3e5790.jpg</filename>
	<path>brown_blight_in_tea11_jpg.rf.849483c9693f6d1e2a253d666d3e5790.jpg</path>
	<source>
		<database>roboflow.ai</database>
	</source>
	<size>
		<width>320</width>
		<height>320</height>
		<depth>3</depth>
	</size>
	<segmented>0</segmented>
	<object>
		<name>Brown Blight</name>
		<pose>Unspecified</pose>
		<truncated>0</truncated>
		<difficult>0</difficult>
		<occluded>0</occluded>
		<bndbox>
			<xmin>71</xmin>
			<xmax>292</xmax>
			<ymin>18</ymin>
			<ymax>321</ymax>
		</bndbox>
	</object>
</annotation>
